bk_db_tools/__init__.py
bk_db_tools/csv_importer.py
bk_db_tools/database.py
bk_db_tools/importer.py
bk_db_tools/settings.py
bk_db_tools/sql_file_executer.py
bk_db_tools/xlsx_data_replace.py
bk_db_tools/xlsx_exporter.py
bk_db_tools/xlsx_importer.py
bk_db_tools-2.1.2.dist-info/LICENSE
bk_db_tools-2.1.2.dist-info/METADATA
bk_db_tools-2.1.2.dist-info/WHEEL
bk_db_tools-2.1.2.dist-info/top_level.txt
bk_db_tools-2.1.2.dist-info/RECORD
