Metadata-Version: 2.1
Name: bk-db-tools
Version: 2.1.2
Summary: bk_db_tools is a set of tools to very rapidly, and with a minimum of effort, work with a relational database.
Home-page: https://github.com/SunnysideAaron/bk_db_tools
Author: Aaron R. Short
Author-email: FuzzyFonzy@yahoo.com
License: UNKNOWN
Project-URL: Wiki, https://github.com/SunnysideAaron/bk_db_tools/wiki
Platform: UNKNOWN
Classifier: Programming Language :: Python :: 3
Classifier: License :: OSI Approved :: Apache Software License
Classifier: Operating System :: OS Independent
Requires-Python: >=3.7
Requires-Dist: openpyxl (~=3.0)
